parseltongue/__init__.py
parseltongue/parseltongue.py
parseltongue_grammar/parseltongue.py
parseltongue-0.3.0.dist-info/LICENSE
parseltongue-0.3.0.dist-info/METADATA
parseltongue-0.3.0.dist-info/WHEEL
parseltongue-0.3.0.dist-info/top_level.txt
parseltongue-0.3.0.dist-info/RECORD
