Metadata-Version: 2.1
Name: parseltongue
Version: 0.3.0
Summary: List of dragonfly grammars to write programs in python
Home-page: https://github.com/sauravmishra1017/Parseltongue
Author: Saurav Mishra
Author-email: sauravmishra1017@gmail.com
License: MIT
Platform: UNKNOWN
Classifier: License :: OSI Approved :: MIT License
Classifier: Programming Language :: Python :: 2
Requires-Dist: dragonfly2
